{
  "columns":[
	  {
	  		"title":"操作",
	  	  "field":"ck",
				"checkbox":"true"
	  },
    {
      "field":"id",
      "title":"ID",
      "halign":"center",
      "width":"15%",
      "hidden":"true",
      "align":"center",
      "editor": "text"
    },
    {
      "field":"username",
      "title":"用户名",
      "halign":"center",
      "width":"17%",
      "align":"center"
    },
    {
      "field":"sex",
      "title":"性别",
      "halign":"center",
      "width":"11%",
      "align":"center"
    },
    {
      "field":"create_time",
      "title":"创建日期",
      "halign":"center",
      "width":"21%",
      "align":"center"
    },
    {
      "field":"birthday",
      "title":"出生日期",
      "halign":"center",
      "width":"21%",
      "align":"center"
    },
    {
      "field":"password",
      "title":"密码",
      "halign":"center",
      "width":"15%",
      "align":"center"
    }  
  ]
}